[
  {
    "pointList": [
      {
        "x": "120.4658",
        "y": "40.22647"
      }
    ],
    "name": "绥中二河口渔港",
    "code": "LNEHKYG",
    "level": 3
  },
  {
    "pointList": [
      {
        "x": "121.0892",
        "y": "40.8611"
      }
    ],
    "name": "锦州中心渔港",
    "code": "LNJZYG",
    "level": 3
  },
  {
    "pointList": [
      {
        "x": "121.7672",
        "y": "40.8858"
      }
    ],
    "name": "盘锦二界沟渔港",
    "code": "LNEJGYG",
    "level": 3
  },
  {
    "pointList": [
      {
        "x": "123.5448",
        "y": "39.7693"
      }
    ],
    "name": "丹东海洋红渔港",
    "code": "LNHYHYG",
    "level": 3
  },
  {
    "pointList": [
      {
        "x": "122.2017",
        "y": "40.3953"
      }
    ],
    "name": "营口光辉渔港",
    "code": "LNGHYG",
    "level": 3
  },
  {
    "pointList": [
      {
        "x": "120",
        "y": "38.5"
      },
      {
        "x": "120",
        "y": "41"
      },
      {
        "x": "122",
        "y": "41"
      },
      {
        "x": "122",
        "y": "38.5"
      }
    ],
    "name": "辽东湾渔场",
    "code": "LNLNWYCH",
    "level": 3
  },
  {
    "pointList": [
      {
        "x": "124",
        "y": "39"
      },
      {
        "x": "124",
        "y": "39.8"
      },
      {
        "x": "125.2",
        "y": "39.8"
      },
      {
        "x": "125.2",
        "y": "39"
      }
    ],
    "name": "海东渔场",
    "code": "LNHDYCH",
    "level": 3
  },
  {
    "pointList": [
      {
        "x": "122",
        "y": "38"
      },
      {
        "x": "122",
        "y": "39.8"
      },
      {
        "x": "124",
        "y": "39.8"
      },
      {
        "x": "124",
        "y": "38"
      }
    ],
    "name": "海洋岛渔场",
    "code": "LNHYDYCH",
    "level": 3
  },
  {
    "pointList": [
      {
        "x": "121.6833",
        "y": "38.8667"
      }
    ],
    "name": "大连市",
    "code": "LNDLS",
    "level": 2
  },
  {
    "pointList": [
      {
        "x": "124.1667",
        "y": "39.8333"
      }
    ],
    "name": "丹东市",
    "code": "LNDDS",
    "level": 2
  },
  {
    "pointList": [
      {
        "x": "121.1199",
        "y": "40.8073"
      }
    ],
    "name": "锦州市",
    "code": "LNJZS",
    "level": 2
  },
  {
    "pointList": [
      {
        "x": "122.1",
        "y": "40.3"
      }
    ],
    "name": "营口市",
    "code": "LNYKS",
    "level": 2
  },
  {
    "pointList": [
      {
        "x": "121.9088",
        "y": "40.7862"
      }
    ],
    "name": "盘锦市",
    "code": "LNPJS",
    "level": 2
  },
  {
    "pointList": [
      {
        "x": "121.0167",
        "y": "40.7"
      }
    ],
    "name": "葫芦岛市",
    "code": "LNHLDS",
    "level": 2
  }
]
